trallnags_hello_python/__init__.py
trallnags_hello_python/main.py
trallnags_hello_python-0.2.0.dist-info/LICENSE
trallnags_hello_python-0.2.0.dist-info/WHEEL
trallnags_hello_python-0.2.0.dist-info/METADATA
trallnags_hello_python-0.2.0.dist-info/RECORD
