Metadata-Version: 2.1
Name: trallnags-hello-python
Version: 0.2.0
Summary: Just a test project
Home-page: https://github.com/trallnag/hello-python
License: Apache-2.0
Author: Tim Schwenke
Author-email: tim.and.trallnag+code@gmail.com
Requires-Python: >=3.8,<4.0
Classifier: License :: OSI Approved :: Apache Software License
Classifier: Programming Language :: Python :: 3
Classifier: Programming Language :: Python :: 3.8
Classifier: Programming Language :: Python :: 3.9
Project-URL: Repository, https://github.com/trallnag/hello-python
